merklepy/__init__.py
merklepy/exception.py
merklepy/hash.py
merklepy/options.py
merklepy/path.py
merklepy/proof.py
merklepy/tree.py
merkle_py-1.2.11.dist-info/METADATA
merkle_py-1.2.11.dist-info/WHEEL
merkle_py-1.2.11.dist-info/top_level.txt
merkle_py-1.2.11.dist-info/RECORD
