Metadata-Version: 2.4
Name: merkle-py
Version: 1.2.11
Summary: Merkle tree for Python
Home-page: https://github.com/cyrildever/merkle-trees/tree/master/packages/py
Author: Cyril Dever
Project-URL: Bug Tracker, https://github.com/cyrildever/merkle-trees/issues
Keywords: python,merkle-tree,merkle
Classifier: Programming Language :: Python :: 3
Classifier: License :: OSI Approved :: MIT License
Classifier: Operating System :: OS Independent
Requires-Python: >=3.6
Dynamic: author
Dynamic: classifier
Dynamic: description
Dynamic: description-content-type
Dynamic: home-page
Dynamic: keywords
Dynamic: project-url
Dynamic: requires-python
Dynamic: summary
